<annotation>
	<folder>train_image_folder</folder>
	<filename>pic_0823-183817_36_aug_63_0_3827_aug_259_0_3200.png</filename>
	<path>/Users/nickk124/research/projects/pismash/PiSmashRepo/objectRecognition/rankDetector/train_image_folder/pic_0823-183817_36_aug_63_0_3827_aug_259_0_3200.png</path>
	<source>
		<database>Unknown</database>
	</source>
	<size>
		<width>1280</width>
		<height>720</height>
		<depth>3</depth>
	</size>
	<segmented>0</segmented>
	<object>
		<name>second</name>
		<pose>Unspecified</pose>
		<truncated>0</truncated>
		<difficult>0</difficult>
		<bndbox>
			<xmin>403</xmin>
			<ymin>307</ymin>
			<xmax>447</xmax>
			<ymax>355</ymax>
		</bndbox>
	</object>
	<object>
		<name>third</name>
		<pose>Unspecified</pose>
		<truncated>0</truncated>
		<difficult>0</difficult>
		<bndbox>
			<xmin>594</xmin>
			<ymin>334</ymin>
			<xmax>631</xmax>
			<ymax>390</ymax>
		</bndbox>
	</object>
	<object>
		<name>first</name>
		<pose>Unspecified</pose>
		<truncated>0</truncated>
		<difficult>0</difficult>
		<bndbox>
			<xmin>763</xmin>
			<ymin>348</ymin>
			<xmax>795</xmax>
			<ymax>407</ymax>
		</bndbox>
	</object>
</annotation>
