<annotation>
	<folder>train_image_folder_unlabeled</folder>
	<filename>pic_0901-212853_23_aug0.jpeg</filename>
	<path>/Users/nickk124/research/projects/pismash/PiSmashRepo/objectRecognition/rankDetector/train_image_folder/pic_0901-212853_23_aug0.jpeg</path>
	<source>
		<database>Unknown</database>
	</source>
	<size>
		<width>1371</width>
		<height>898</height>
		<depth>3</depth>
	</size>
	<segmented>0</segmented>
	<object>
		<name>third</name>
		<pose>Unspecified</pose>
		<truncated>1</truncated>
		<difficult>0</difficult>
		<bndbox>
			<xmin>588</xmin>
			<ymin>72</ymin>
			<xmax>644</xmax>
			<ymax>112</ymax>
		</bndbox>
	</object>
	<object>
		<name>first</name>
		<pose>Unspecified</pose>
		<truncated>1</truncated>
		<difficult>0</difficult>
		<bndbox>
			<xmin>684</xmin>
			<ymin>86</ymin>
			<xmax>741</xmax>
			<ymax>142</ymax>
		</bndbox>
	</object>
	<object>
		<name>sixth</name>
		<pose>Unspecified</pose>
		<truncated>0</truncated>
		<difficult>0</difficult>
		<bndbox>
			<xmin>814</xmin>
			<ymin>115</ymin>
			<xmax>863</xmax>
			<ymax>164</ymax>
		</bndbox>
	</object>
	<object>
		<name>seventh</name>
		<pose>Unspecified</pose>
		<truncated>0</truncated>
		<difficult>0</difficult>
		<bndbox>
			<xmin>918</xmin>
			<ymin>140</ymin>
			<xmax>969</xmax>
			<ymax>190</ymax>
		</bndbox>
	</object>
	<object>
		<name>fourth</name>
		<pose>Unspecified</pose>
		<truncated>0</truncated>
		<difficult>0</difficult>
		<bndbox>
			<xmin>1025</xmin>
			<ymin>167</ymin>
			<xmax>1073</xmax>
			<ymax>215</ymax>
		</bndbox>
	</object>
</annotation>